semantic_complexity/__init__.py
semantic_complexity/analyzers/__init__.py
semantic_complexity/analyzers/bread.py
semantic_complexity/analyzers/cheese.py
semantic_complexity/analyzers/ham.py
semantic_complexity/analyzers/test_discovery.py
semantic_complexity/budget/__init__.py
semantic_complexity/budget/tracker.py
semantic_complexity/canonical/__init__.py
semantic_complexity/cli/__init__.py
semantic_complexity/energy/__init__.py
semantic_complexity/energy/convergence.py
semantic_complexity/energy/delta.py
semantic_complexity/energy/potential.py
semantic_complexity/flux/__init__.py
semantic_complexity/flux/boundary.py
semantic_complexity/flux/degradation.py
semantic_complexity/gate/__init__.py
semantic_complexity/gate/mvp.py
semantic_complexity/gate/waiver.py
semantic_complexity/gate/adr/__init__.py
semantic_complexity/gate/adr/expiry.py
semantic_complexity/gate/adr/parser.py
semantic_complexity/gate/adr/schema.py
semantic_complexity/gate/adr/validator.py
semantic_complexity/graph/__init__.py
semantic_complexity/graph/edge.py
semantic_complexity/graph/entity.py
semantic_complexity/graph/metrics.py
semantic_complexity/graph/snapshot.py
semantic_complexity/graph/store.py
semantic_complexity/mcp/__init__.py
semantic_complexity/measurement/__init__.py
semantic_complexity/measurement/deviation.py
semantic_complexity/measurement/evidence.py
semantic_complexity/measurement/hodge.py
semantic_complexity/measurement/vector.py
semantic_complexity/protected/__init__.py
semantic_complexity/protected/patterns.py
semantic_complexity/recommend/__init__.py
semantic_complexity/recommend/gradient.py
semantic_complexity/simplex/__init__.py
semantic_complexity/simplex/equilibrium.py
semantic_complexity/simplex/labeler.py
semantic_complexity/simplex/normalizer.py
semantic_complexity/types/__init__.py
semantic_complexity/types/axis.py
semantic_complexity/types/module.py
semantic_complexity/types/profile.py
semantic_complexity/types/score.py
semantic_complexity/view/__init__.py
semantic_complexity-0.0.25.dist-info/METADATA
semantic_complexity-0.0.25.dist-info/WHEEL
semantic_complexity-0.0.25.dist-info/entry_points.txt
semantic_complexity-0.0.25.dist-info/RECORD
