Metadata-Version: 2.4
Name: semantic-complexity
Version: 0.0.25
Summary: Multi-dimensional code complexity analyzer
Project-URL: Homepage, https://github.com/yscha88/semantic-complexity
Project-URL: Repository, https://github.com/yscha88/semantic-complexity
Project-URL: Issues, https://github.com/yscha88/semantic-complexity/issues
Author-email: yscha88 <clmfkilu@gmail.com>
License: MIT
Keywords: code-analysis,cognitive,complexity,cyclomatic,metrics
Classifier: Development Status :: 3 - Alpha
Classifier: Intended Audience :: Developers
Classifier: License :: OSI Approved :: MIT License
Classifier: Programming Language :: Python :: 3
Classifier: Programming Language :: Python :: 3.10
Classifier: Programming Language :: Python :: 3.11
Classifier: Programming Language :: Python :: 3.12
Classifier: Topic :: Software Development :: Quality Assurance
Requires-Python: >=3.10
Requires-Dist: click>=8.0
Requires-Dist: mcp>=1.25
Requires-Dist: rich>=13.0
Provides-Extra: all
Requires-Dist: numpy>=1.24; extra == 'all'
Requires-Dist: pyyaml>=6.0; extra == 'all'
Provides-Extra: dev
Requires-Dist: mypy>=1.8.0; extra == 'dev'
Requires-Dist: numpy>=1.24; extra == 'dev'
Requires-Dist: pytest-cov>=4.0.0; extra == 'dev'
Requires-Dist: pytest>=8.0.0; extra == 'dev'
Requires-Dist: pyyaml>=6.0; extra == 'dev'
Requires-Dist: ruff>=0.1.0; extra == 'dev'
Provides-Extra: numpy
Requires-Dist: numpy>=1.24; extra == 'numpy'
Provides-Extra: yaml
Requires-Dist: pyyaml>=6.0; extra == 'yaml'
